pocketchemist/__init__.py
pocketchemist/cli/__init__.py
pocketchemist/cli/hookimpls.py
pocketchemist/cli/hookspecs.py
pocketchemist/cli/main.py
pocketchemist/cli/setup.py
pocketchemist/modules/__init__.py
pocketchemist/modules/modules.py
pocketchemist/processors/__init__.py
pocketchemist/processors/processor.py
pocketchemist/utils/__init__.py
pocketchemist/utils/classes.py
pocketchemist/utils/list.py
pocketchemist/utils/types.py
pocketchemist-0.1.3.dist-info/entry_points.txt
pocketchemist-0.1.3.dist-info/WHEEL
pocketchemist-0.1.3.dist-info/METADATA
pocketchemist-0.1.3.dist-info/RECORD
